aifoundary/__init__.py
aifoundary/cli.py
aifoundary/aifoundary/core/__init__.py
aifoundary/aifoundary/core/uaal/__init__.py
aifoundary/audit/__init__.py
aifoundary/audit/audit.py
aifoundary/audit/cli.py
aifoundary/audit/export.py
aifoundary/audit/pdf.py
aifoundary/compliance/__init__.py
aifoundary/connectors/__init__.py
aifoundary/core/__init__.py
aifoundary/core/knowledge_vault/__init__.py
aifoundary/core/knowledge_vault/api.py
aifoundary/core/knowledge_vault/provenance.py
aifoundary/core/knowledge_vault/access/audit_log.py
aifoundary/core/knowledge_vault/access/permissions.py
aifoundary/core/knowledge_vault/access/retrieval.py
aifoundary/core/knowledge_vault/adapters/knowledge_vault.py
aifoundary/core/knowledge_vault/demos/demo_task_flow.py
aifoundary/core/knowledge_vault/embeddings/embedding_provider.py
aifoundary/core/knowledge_vault/ingest/api_ingestor.py
aifoundary/core/knowledge_vault/ingest/file_ingestor.py
aifoundary/core/knowledge_vault/ingest/repo_ingestor.py
aifoundary/core/knowledge_vault/store/metadata_db.py
aifoundary/core/knowledge_vault/store/vector_store.py
aifoundary/core/knowledge_vault/store/versioning.py
aifoundary/core/mcp_firewall/__init__.py
aifoundary/core/mcp_firewall/firewall.py
aifoundary/core/mcp_firewall/policy.py
aifoundary/core/mcp_firewall/tool_gateway.py
aifoundary/core/mcp_firewall/uaal_bridge.py
aifoundary/core/mcp_firewall/cli/__init__.py
aifoundary/core/mcp_firewall/cli/mcp_check.py
aifoundary/core/mcp_firewall/schemas/__init__.py
aifoundary/core/mcp_firewall/schemas/action.py
aifoundary/core/uaal/__init__.py
aifoundary/core/uaal/decision_graph.py
aifoundary/core/uaal/decision_store.py
aifoundary/core/uaal/decision_store_sqlite.py
aifoundary/core/uaal/record.py
aifoundary/eval/__init__.py
aifoundary/policy/__init__.py
aifoundary/policy/loader.py
aifoundary/rag/__init__.py
aifoundary/rag/auto_retry.py
aifoundary/rag/coverage.py
aifoundary/rag/rewrite.py
aifoundary/rag/secure_rag.py
aifoundary-3.1.0.dist-info/METADATA
aifoundary-3.1.0.dist-info/WHEEL
aifoundary-3.1.0.dist-info/entry_points.txt
aifoundary-3.1.0.dist-info/top_level.txt
aifoundary-3.1.0.dist-info/RECORD
