Metadata-Version: 2.4
Name: aifoundary
Version: 3.1.0
Summary: AI Operating Control Plane with RAG governance, MCP authorization, and audit-grade decision reports
Requires-Python: >=3.9
Requires-Dist: pydantic>=2.0
Requires-Dist: pyyaml>=6.0
Requires-Dist: reportlab>=4.0
Provides-Extra: uaal
Requires-Dist: uaal-core>=0.1.3; extra == "uaal"
